littlebaker/__init__.py
littlebaker/beemovie.py
littlebaker/littlebaker.py
littlebaker/test.py
tests/__init__.py
tests/test_dates.py
tests/test_make.py
littlebaker-0.0.1.dist-info/LICENSE
littlebaker-0.0.1.dist-info/METADATA
littlebaker-0.0.1.dist-info/WHEEL
littlebaker-0.0.1.dist-info/top_level.txt
littlebaker-0.0.1.dist-info/RECORD
