Metadata-Version: 2.1
Name: littlebaker
Version: 0.0.1
Summary: Package to auto-generate lists, dictionaries, arrays, matricies (list-of-lists), json, csv files, and Pandas Dataframes
Home-page: https://github.com/MiConnell/littlebaker
Author: Michael Connell
Author-email: connellmp@gmail.com
License: UNKNOWN
Platform: UNKNOWN
Classifier: Programming Language :: Python :: 3
Classifier: License :: OSI Approved :: MIT License
Classifier: Operating System :: OS Independent
Requires-Python: >=3.6
